Metadata-Version: 2.1
Name: jawa-fixed
Version: 2.4.0
Summary: Doing fun stuff with JVM ClassFiles.
Home-page: https://github.com/GiantTreeLP/jawa-fixed
Maintainer: GiantTree
Maintainer-email: gianttree@groundmc.net
License: UNKNOWN
Keywords: java,disassembly,disassembler,assembly
Platform: UNKNOWN
Classifier: Programming Language :: Python
Classifier: License :: OSI Approved :: MIT License
Classifier: Operating System :: OS Independent
Classifier: Development Status :: 3 - Alpha
Classifier: Intended Audience :: Developers
Classifier: Topic :: Software Development :: Disassemblers
Classifier: Topic :: Software Development :: Assemblers
Requires-Python: >=3.8
License-File: LICENCE
Requires-Dist: click (>=5.0)
Requires-Dist: mutf8 (>=1.0.5)
Provides-Extra: dev
Requires-Dist: pytest ; extra == 'dev'
Requires-Dist: sphinx ; extra == 'dev'
Requires-Dist: sphinx-rtd-theme ; extra == 'dev'
Requires-Dist: sphinx-click ; extra == 'dev'
Requires-Dist: ghp-import ; extra == 'dev'
Requires-Dist: pyyaml ; extra == 'dev'
Requires-Dist: ipython ; extra == 'dev'
Requires-Dist: twine ; extra == 'dev'
Requires-Dist: wheel ; extra == 'dev'
Requires-Dist: bump2version ; extra == 'dev'
Requires-Dist: flake8 ; extra == 'dev'
